MANIFEST.in
README.md
setup.py
jupytertweak/__init__.py
jupytertweak/disp.py
jupytertweak/tictoc.py
jupytertweak.egg-info/PKG-INFO
jupytertweak.egg-info/SOURCES.txt
jupytertweak.egg-info/dependency_links.txt
jupytertweak.egg-info/not-zip-safe
jupytertweak.egg-info/requires.txt
jupytertweak.egg-info/top_level.txt