Metadata-Version: 2.1
Name: jupytertweak
Version: 0.2.0
Summary: Tweaks for jupyter notebooks
Home-page: http://github.com/kmedian/jupytertweak
Author: Ulf Hamster
Author-email: 554c46@gmail.com
License: MIT
Platform: UNKNOWN
Requires-Python: >=3.6
